thoughtspot_rest_api/__init__.py
thoughtspot_rest_api/_version.py
thoughtspot_rest_api/details_objects.py
thoughtspot_rest_api/tsrestapiv1.py
thoughtspot_rest_api/tsrestapiv2.py
thoughtspot_rest_api-2.0.1.dist-info/METADATA
thoughtspot_rest_api-2.0.1.dist-info/WHEEL
thoughtspot_rest_api-2.0.1.dist-info/top_level.txt
thoughtspot_rest_api-2.0.1.dist-info/RECORD
