Metadata-Version: 2.4
Name: thoughtspot_rest_api
Version: 2.0.1
Summary: Library implementing ThoughtSpot REST API V2.0 and V1
Home-page: https://github.com/thoughtspot/thoughtspot_rest_api
Author: Bryant Howell
Author-email: bryant.howell@thoughtspot.com
License: MIT
Project-URL: Documentation, https://github.com/thoughtspot/thoughtspot_rest_api#readme
Project-URL: Bug Tracker, https://github.com/thoughtspot/thoughtspot_rest_api/issues
Classifier: Programming Language :: Python :: 3
Classifier: License :: OSI Approved :: MIT License
Classifier: Operating System :: OS Independent
Requires-Python: >=3.6
Requires-Dist: requests
Requires-Dist: requests_toolbelt
